{
  "events": [
    {
      "date": "Nov 18",
      "time": "8:30 AM ET",
      "event": "US Housing Starts & Building Permits (October)",
      "description": "Key gauge of construction activity and housing sector health",
      "importance": "high"
    },
    {
      "date": "Nov 18",
      "time": "9:15 AM ET",
      "event": "Fed Industrial Production & Capacity Utilization (October)",
      "description": "Measures output of US factories and utilization rates, signals economic momentum",
      "importance": "medium"
    },
    {
      "date": "Nov 18",
      "time": "All Day",
      "event": "Fed Governor Waller Speech",
      "description": "Fed commentary can shift rate expectations and market sentiment",
      "importance": "high"
    },
    {
      "date": "Nov 19",
      "time": "8:30 AM ET",
      "event": "US Activities of Foreign Affiliates Report",
      "description": "Insight into multinational activity, limited direct market impact",
      "importance": "low"
    },
    {
      "date": "Nov 19",
      "time": "All Day",
      "event": "Fed Vice Chair Jefferson Speech",
      "description": "Fed leadership remarks can influence policy outlook",
      "importance": "high"
    },
    {
      "date": "Nov 20",
      "time": "8:30 AM ET",
      "event": "Weekly Jobless Claims",
      "description": "Timely labor market indicator, watched for signs of economic stress",
      "importance": "high"
    },
    {
      "date": "Nov 20",
      "time": "10:00 AM ET",
      "event": "Existing Home Sales (October)",
      "description": "Measures housing market demand and consumer confidence",
      "importance": "medium"
    },
    {
      "date": "Nov 20",
      "time": "All Day",
      "event": "Fed President Williams Speech",
      "description": "Fed regional president views on policy and economy",
      "importance": "medium"
    },
    {
      "date": "Nov 21",
      "time": "10:00 AM ET",
      "event": "University of Michigan Consumer Sentiment (Final, November)",
      "description": "Consumer confidence impacts spending and market risk appetite",
      "importance": "high"
    },
    {
      "date": "Nov 21",
      "time": "All Day",
      "event": "Monthly Options Expiration (OPEX)",
      "description": "Options expiration can increase volatility and trading volume",
      "importance": "medium"
    },
    {
      "date": "Nov 22",
      "time": "All Day",
      "event": "Fed Chair Powell Speech",
      "description": "Fed Chair remarks are the most influential for policy and markets",
      "importance": "high"
    },
    {
      "date": "Nov 25",
      "time": "8:30 AM ET",
      "event": "US Advance International Trade in Goods (October)",
      "description": "Trade balance affects GDP forecasts and currency markets",
      "importance": "medium"
    },
    {
      "date": "Nov 25",
      "time": "8:30 AM ET",
      "event": "US Durable Goods Orders (October)",
      "description": "Key indicator of business investment and manufacturing demand",
      "importance": "high"
    },
    {
      "date": "Nov 25",
      "time": "10:00 AM ET",
      "event": "New Home Sales (October)",
      "description": "Reflects housing demand and construction sector strength",
      "importance": "medium"
    },
    {
      "date": "Nov 26",
      "time": "8:30 AM ET",
      "event": "US GDP 3Q 2025 (Second Estimate)",
      "description": "Quarterly economic growth, critical for market and Fed outlook",
      "importance": "high"
    },
    {
      "date": "Nov 26",
      "time": "8:30 AM ET",
      "event": "Personal Income & Outlays, PCE Inflation (October)",
      "description": "Fed's preferred inflation gauge, key for rate expectations",
      "importance": "high"
    },
    {
      "date": "Nov 26",
      "time": "10:00 AM ET",
      "event": "Fed Beige Book",
      "description": "Anecdotal economic report used by Fed for policy decisions",
      "importance": "high"
    },
    {
      "date": "Nov 27",
      "time": "8:30 AM ET",
      "event": "Weekly Jobless Claims",
      "description": "Labor market update, especially relevant ahead of holidays",
      "importance": "high"
    },
    {
      "date": "Nov 28",
      "time": "All Day",
      "event": "Fed President Daly Speech",
      "description": "Fed regional president views on economy and policy",
      "importance": "medium"
    },
    {
      "date": "Dec 2",
      "time": "10:00 AM ET",
      "event": "ISM Manufacturing PMI (November)",
      "description": "Key manufacturing sector activity gauge, signals economic direction",
      "importance": "high"
    },
    {
      "date": "Dec 3",
      "time": "8:15 AM ET",
      "event": "ADP Private Payrolls (November)",
      "description": "Early read on US employment trends ahead of NFP",
      "importance": "high"
    },
    {
      "date": "Dec 3",
      "time": "10:00 AM ET",
      "event": "JOLTS Job Openings (October)",
      "description": "Measures labor demand and tightness, watched by Fed",
      "importance": "medium"
    },
    {
      "date": "Dec 4",
      "time": "8:30 AM ET",
      "event": "US Initial Jobless Claims",
      "description": "Weekly labor market health check",
      "importance": "high"
    },
    {
      "date": "Dec 4",
      "time": "10:00 AM ET",
      "event": "ISM Services PMI (November)",
      "description": "Services sector activity, largest part of US economy",
      "importance": "high"
    },
    {
      "date": "Dec 5",
      "time": "8:30 AM ET",
      "event": "US Non-Farm Payrolls & Unemployment Rate (November)",
      "description": "Most important labor market report, drives Fed and market moves",
      "importance": "high"
    },
    {
      "date": "Dec 5",
      "time": "10:00 AM ET",
      "event": "University of Michigan Consumer Sentiment (Prelim, December)",
      "description": "Early read on consumer confidence for December",
      "importance": "high"
    },
    {
      "date": "Dec 9",
      "time": "All Day",
      "event": "Treasury 10-Year Note Auction",
      "description": "Major Treasury auction, impacts yields and risk assets",
      "importance": "high"
    },
    {
      "date": "Dec 10",
      "time": "8:30 AM ET",
      "event": "US CPI (November)",
      "description": "Critical inflation report, directly impacts Fed policy path",
      "importance": "high"
    },
    {
      "date": "Dec 11",
      "time": "8:30 AM ET",
      "event": "US PPI (November)",
      "description": "Producer inflation, upstream price pressures for CPI",
      "importance": "high"
    },
    {
      "date": "Dec 11",
      "time": "2:00 PM ET",
      "event": "Treasury 30-Year Bond Auction",
      "description": "Long-term Treasury auction, affects rates and equities",
      "importance": "high"
    },
    {
      "date": "Dec 12",
      "time": "All Day",
      "event": "ECB Policy Meeting & Rate Decision",
      "description": "ECB decisions impact global rates and risk sentiment",
      "importance": "high"
    },
    {
      "date": "Dec 12",
      "time": "All Day",
      "event": "Monthly Options Expiration (OPEX)",
      "description": "Options expiration can drive volatility and market flows",
      "importance": "medium"
    },
    {
      "date": "Dec 13",
      "time": "All Day",
      "event": "FOMC Meeting Begins (Dec 13-14)",
      "description": "Fed policy meeting, sets interest rate and guidance",
      "importance": "high"
    },
    {
      "date": "Dec 13",
      "time": "After Market",
      "event": "Oracle (ORCL) Earnings",
      "description": "Major tech earnings, signals enterprise IT demand",
      "importance": "medium"
    },
    {
      "date": "Dec 14",
      "time": "2:00 PM ET",
      "event": "FOMC Rate Decision & Powell Press Conference",
      "description": "Fed decision and Chair's remarks are the most market-moving events",
      "importance": "high"
    }
  ],
  "timestamp": "2025-11-18 07:26:17",
  "cached": false
}