{
  "LASR": {
    "preference": "favorite",
    "created_at": "2026-01-03T18:59:58.654399",
    "updated_at": "2026-01-03T18:59:58.654412"
  },
  "APP": {
    "preference": "favorite",
    "created_at": "2026-01-03T18:59:58.657040",
    "updated_at": "2026-01-03T18:59:58.657049"
  },
  "HROW": {
    "preference": "favorite",
    "created_at": "2026-01-03T18:59:58.657865",
    "updated_at": "2026-01-03T18:59:58.657873"
  },
  "NIC": {
    "preference": "dislike",
    "created_at": "2026-01-03T18:59:58.658636",
    "updated_at": "2026-01-03T18:59:58.658641"
  },
  "TGB": {
    "preference": "dislike",
    "created_at": "2026-01-03T18:59:58.659608",
    "updated_at": "2026-01-03T18:59:58.659617"
  },
  "PRCT": {
    "preference": "favorite",
    "created_at": "2026-01-03T18:59:58.660538",
    "updated_at": "2026-01-03T18:59:58.660545"
  },
  "VOYG": {
    "preference": "favorite",
    "created_at": "2026-01-03T18:59:58.661293",
    "updated_at": "2026-01-03T18:59:58.661300"
  },
  "SPB": {
    "preference": "dislike",
    "created_at": "2026-01-03T18:59:58.662094",
    "updated_at": "2026-01-03T18:59:58.662100"
  },
  "ONDS": {
    "preference": "favorite",
    "created_at": "2026-01-03T18:59:58.662834",
    "updated_at": "2026-01-03T18:59:58.662840"
  },
  "SIDU": {
    "preference": "favorite",
    "created_at": "2026-01-04T11:54:32.419481",
    "updated_at": "2026-01-04T11:54:32.419647"
  }
}